binary_wheel_builder/__init__.py
binary_wheel_builder/__main__.py
binary_wheel_builder/__version__.py
binary_wheel_builder/api/__init__.py
binary_wheel_builder/api/build.py
binary_wheel_builder/api/meta.py
binary_wheel_builder/api/well_known_platforms.py
binary_wheel_builder/api/wheel_sources/__init__.py
binary_wheel_builder/api/wheel_sources/exceptions.py
binary_wheel_builder/api/wheel_sources/github.py
binary_wheel_builder/api/wheel_sources/github_test.py
binary_wheel_builder/api/wheel_sources/gitlab_package_registry.py
binary_wheel_builder/api/wheel_sources/gitlab_package_registry_test.py
binary_wheel_builder/api/wheel_sources/platform_based_file.py
binary_wheel_builder/api/wheel_sources/platform_based_file_test.py
binary_wheel_builder/api/wheel_sources/static.py
binary_wheel_builder/cli/__init__.py
binary_wheel_builder/cli/config_file.py
binary_wheel_builder/cli/main.py
binary_wheel_builder/cli/yaml.py
binary_wheel_builder/cli/yaml_test.py
binary_wheel_builder/wheel/__init__.py
binary_wheel_builder/wheel/reproducible.py
binary_wheel_builder/wheel/reproducible_test.py
binary_wheel_builder/wheel/util.py
binary_wheel_builder/wheel/util_test.py
binary_wheel_builder/wrapper_templates.py
binary_wheel_builder/wrapper_templates_test.py
binary_wheel_builder-3.14.2.dist-info/LICENSE
binary_wheel_builder-3.14.2.dist-info/METADATA
binary_wheel_builder-3.14.2.dist-info/WHEEL
binary_wheel_builder-3.14.2.dist-info/entry_points.txt
binary_wheel_builder-3.14.2.dist-info/RECORD
