Metadata-Version: 2.3
Name: binary_wheel_builder
Version: 3.14.2
Summary: Bundle CLI applications or other binary data as wheel to use them in code or as standalone binary
Author: Timo Reymann
Author-email: mail@timo-reymann.de
Requires-Python: >3.9
Classifier: Development Status :: 5 - Production/Stable
Classifier: Environment :: Console
Classifier: Environment :: MacOS X
Classifier: Intended Audience :: Developers
Classifier: Operating System :: POSIX
Classifier: Operating System :: Unix
Classifier: Programming Language :: Python :: 3
Classifier: Programming Language :: Python :: 3.10
Classifier: Programming Language :: Python :: 3.11
Classifier: Programming Language :: Python :: 3.12
Classifier: Programming Language :: Python :: 3.13
Classifier: Topic :: Software Development :: Build Tools
Classifier: Topic :: Software Development :: Code Generators
Classifier: Topic :: System :: Software Distribution
Provides-Extra: cli
Requires-Dist: pydantic (>=2.5.3,<3.0.0)
Requires-Dist: pyyaml (>=6.0.1,<7.0.0) ; extra == "cli"
Requires-Dist: wheel (>0.30.0)
Project-URL: Bug Tracker, https://github.com/timo-reymann/python-binary-wheel-builder/issues
Project-URL: Repository, https://github.com/timo-reymann/python-binary-wheel-builder
